Metadata-Version: 2.4
Name: unfold_extra
Version: 0.1.0
Summary: Unofficial extra for Django Unfold Admin. Supports django-parler and django-cms.
Project-URL: Homepage, https://github.com/metaforx/django-unfold-extra
Author-email: Marc Widmer <marc@koga.cx>
Classifier: Operating System :: OS Independent
Classifier: Programming Language :: Python :: 3
Requires-Python: >=3.6
Requires-Dist: django-cms==5.0.0a1
Requires-Dist: django-parler~=2.3
Requires-Dist: django-unfold
